postgresql_deepgeo/__init__.py
postgresql_deepgeo/function.py
postgresql_deepgeo-0.0.3.dist-info/LICENSE
postgresql_deepgeo-0.0.3.dist-info/METADATA
postgresql_deepgeo-0.0.3.dist-info/WHEEL
postgresql_deepgeo-0.0.3.dist-info/top_level.txt
postgresql_deepgeo-0.0.3.dist-info/RECORD
