Metadata-Version: 2.1
Name: postgresql-deepgeo
Version: 0.0.3
Summary: Easy Deep Learning
Home-page: https://github.com/Sotaneum/PostgreSQL-DeepGeo
Author: Donggun LEE
Author-email: gnyotnu39@gmail.com
License: MIT
Platform: UNKNOWN
Classifier: License :: OSI Approved :: MIT License
